{"self.active_measure_width": 16, "self.n_rows_skipped": 0, "self.row_gap": 2, "self.x_gap": 6, "self.mode": "EDIT", "_track_": "{\"0\":{\"0\":{\"is_rest\":false,\"length\":0.0,\"note\":\"A/3\",\"starting_point\":0.0,\"string_assignment\":2},\"1\":{\"is_rest\":false,\"length\":0.0,\"note\":\"C/4\",\"starting_point\":0.5,\"string_assignment\":1},\"2\":{\"is_rest\":false,\"length\":0.0,\"note\":\"B/3\",\"starting_point\":0.75,\"string_assignment\":1},\"3\":{\"is_rest\":false,\"length\":0.0,\"note\":\"A/3\",\"starting_point\":0.875,\"string_assignment\":2},\"ann_count\":4,\"count\":4,\"total_count\":4},\"1\":{\"0\":{\"is_rest\":false,\"length\":0.0,\"note\":\"B/3\",\"starting_point\":0.0,\"string_assignment\":1},\"1\":{\"is_rest\":false,\"length\":0.0,\"note\":\"E/4\",\"starting_point\":0.25,\"string_assignment\":0},\"2\":{\"is_rest\":false,\"length\":0.0,\"note\":\"E/3\",\"starting_point\":0.5,\"string_assignment\":3},\"ann_count\":3,\"count\":3,\"total_count\":3},\"10\":{\"0\":{\"is_rest\":false,\"length\":0.0,\"note\":\"A/3\",\"starting_point\":0.0,\"string_assignment\":2},\"1\":{\"is_rest\":false,\"length\":0.0,\"note\":\"C/4\",\"starting_point\":0.5,\"string_assignment\":1},\"2\":{\"is_rest\":false,\"length\":0.0,\"note\":\"B/3\",\"starting_point\":0.75,\"string_assignment\":1},\"3\":{\"is_rest\":false,\"length\":0.0,\"note\":\"A/3\",\"starting_point\":0.875,\"string_assignment\":2},\"ann_count\":4,\"count\":4,\"total_count\":4},\"11\":{\"0\":{\"is_rest\":false,\"length\":0.0,\"note\":\"Ab/3\",\"starting_point\":0.0,\"string_assignment\":2},\"ann_count\":1,\"count\":1,\"total_count\":1},\"12\":{\"0\":{\"is_rest\":false,\"length\":0.0,\"note\":\"A/3\",\"starting_point\":0.0,\"string_assignment\":2},\"1\":{\"is_rest\":false,\"length\":0.0,\"note\":\"C/4\",\"starting_point\":0.5,\"string_assignment\":1},\"2\":{\"is_rest\":false,\"length\":0.0,\"note\":\"B/3\",\"starting_point\":0.75,\"string_assignment\":1},\"3\":{\"is_rest\":false,\"length\":0.0,\"note\":\"A/3\",\"starting_point\":0.875,\"string_assignment\":2},\"ann_count\":4,\"count\":4,\"total_count\":4},\"13\":{\"0\":{\"is_rest\":false,\"length\":0.0,\"note\":\"B/3\",\"starting_point\":0.0,\"string_assignment\":1},\"1\":{\"is_rest\":false,\"length\":0.0,\"note\":\"E/4\",\"starting_point\":0.25,\"string_assignment\":0},\"2\":{\"is_rest\":false,\"length\":0.0,\"note\":\"E/3\",\"starting_point\":0.5,\"string_assignment\":3},\"3\":{\"is_rest\":false,\"length\":0.0,\"note\":\"E/3\",\"starting_point\":0.75,\"string_assignment\":3},\"ann_count\":4,\"count\":4,\"total_count\":4},\"14\":{\"0\":{\"is_rest\":false,\"length\":0.0,\"note\":\"F/3\",\"starting_point\":0.0,\"string_assignment\":3},\"1\":{\"is_rest\":false,\"length\":0.0,\"note\":\"G/3\",\"starting_point\":0.125,\"string_assignment\":2},\"2\":{\"is_rest\":false,\"length\":0.0,\"note\":\"A/3\",\"starting_point\":0.25,\"string_assignment\":2},\"3\":{\"is_rest\":false,\"length\":0.0,\"note\":\"B/3\",\"starting_point\":0.375,\"string_assignment\":1},\"4\":{\"is_rest\":false,\"length\":0.0,\"note\":\"C/4\",\"starting_point\":0.5,\"string_assignment\":1},\"5\":{\"is_rest\":false,\"length\":0.0,\"note\":\"B/3\",\"starting_point\":0.75,\"string_assignment\":1},\"ann_count\":6,\"count\":6,\"total_count\":6},\"15\":{\"0\":{\"is_rest\":false,\"length\":0.0,\"note\":\"A/3\",\"starting_point\":0.0,\"string_assignment\":2},\"1\":{\"color\":6,\"starting_point\":0.9900000095367432,\"text\":\"@\"},\"ann_count\":2,\"count\":1,\"total_count\":2},\"16\":{\"0\":{\"is_rest\":false,\"length\":0.0,\"note\":\"E/4\",\"starting_point\":0.0,\"string_assignment\":0},\"1\":{\"is_rest\":false,\"length\":0.0,\"note\":\"E/4\",\"starting_point\":0.25,\"string_assignment\":0},\"2\":{\"is_rest\":false,\"length\":0.0,\"note\":\"E/4\",\"starting_point\":0.5,\"string_assignment\":0},\"3\":{\"is_rest\":false,\"length\":0.0,\"note\":\"E/4\",\"starting_point\":0.75,\"string_assignment\":0},\"ann_count\":4,\"count\":4,\"total_count\":4},\"17\":{\"0\":{\"is_rest\":false,\"length\":0.0,\"note\":\"F/4\",\"starting_point\":0.0,\"string_assignment\":0},\"1\":{\"is_rest\":false,\"length\":0.0,\"note\":\"E/4\",\"starting_point\":0.125,\"string_assignment\":0},\"2\":{\"is_rest\":false,\"length\":0.0,\"note\":\"E/4\",\"starting_point\":0.25,\"string_assignment\":0},\"3\":{\"is_rest\":false,\"length\":0.0,\"note\":\"D/4\",\"starting_point\":0.375,\"string_assignment\":1},\"4\":{\"is_rest\":false,\"length\":0.0,\"note\":\"D/4\",\"starting_point\":0.5,\"string_assignment\":1},\"ann_count\":5,\"count\":5,\"total_count\":5},\"18\":{\"0\":{\"is_rest\":false,\"length\":0.0,\"note\":\"D/4\",\"starting_point\":0.0,\"string_assignment\":1},\"1\":{\"is_rest\":false,\"length\":0.0,\"note\":\"D/4\",\"starting_point\":0.25,\"string_assignment\":1},\"2\":{\"is_rest\":false,\"length\":0.0,\"note\":\"D/4\",\"starting_point\":0.5,\"string_assignment\":1},\"3\":{\"is_rest\":false,\"length\":0.0,\"note\":\"D/4\",\"starting_point\":0.75,\"string_assignment\":1},\"ann_count\":4,\"count\":4,\"total_count\":4},\"19\":{\"0\":{\"is_rest\":false,\"length\":0.0,\"note\":\"E/4\",\"starting_point\":0.0,\"string_assignment\":0},\"1\":{\"is_rest\":false,\"length\":0.0,\"note\":\"D/4\",\"starting_point\":0.125,\"string_assignment\":1},\"2\":{\"is_rest\":false,\"length\":0.0,\"note\":\"D/4\",\"starting_point\":0.25,\"string_assignment\":1},\"3\":{\"is_rest\":false,\"length\":0.0,\"note\":\"C/4\",\"starting_point\":0.375,\"string_assignment\":1},\"4\":{\"is_rest\":false,\"length\":0.0,\"note\":\"C/4\",\"starting_point\":0.5,\"string_assignment\":1},\"ann_count\":5,\"count\":5,\"total_count\":5},\"2\":{\"0\":{\"is_rest\":false,\"length\":0.0,\"note\":\"A/3\",\"starting_point\":0.0,\"string_assignment\":2},\"1\":{\"is_rest\":false,\"length\":0.0,\"note\":\"C/4\",\"starting_point\":0.5,\"string_assignment\":1},\"2\":{\"is_rest\":false,\"length\":0.0,\"note\":\"B/3\",\"starting_point\":0.75,\"string_assignment\":1},\"3\":{\"is_rest\":false,\"length\":0.0,\"note\":\"A/3\",\"starting_point\":0.875,\"string_assignment\":2},\"ann_count\":4,\"count\":4,\"total_count\":4},\"20\":{\"0\":{\"is_rest\":false,\"length\":0.0,\"note\":\"C/4\",\"starting_point\":0.0,\"string_assignment\":1},\"1\":{\"is_rest\":false,\"length\":0.0,\"note\":\"C/4\",\"starting_point\":0.25,\"string_assignment\":1},\"2\":{\"is_rest\":false,\"length\":0.0,\"note\":\"C/4\",\"starting_point\":0.5,\"string_assignment\":1},\"3\":{\"is_rest\":false,\"length\":0.0,\"note\":\"B/3\",\"starting_point\":0.75,\"string_assignment\":1},\"4\":{\"is_rest\":false,\"length\":0.0,\"note\":\"C/4\",\"starting_point\":0.875,\"string_assignment\":1},\"ann_count\":5,\"count\":5,\"total_count\":5},\"21\":{\"0\":{\"is_rest\":false,\"length\":0.0,\"note\":\"D/4\",\"starting_point\":0.0,\"string_assignment\":1},\"1\":{\"is_rest\":false,\"length\":0.0,\"note\":\"A/3\",\"starting_point\":0.25,\"string_assignment\":2},\"2\":{\"is_rest\":false,\"length\":0.0,\"note\":\"D/4\",\"starting_point\":0.5,\"string_assignment\":1},\"ann_count\":3,\"count\":3,\"total_count\":3},\"22\":{\"0\":{\"is_rest\":false,\"length\":0.0,\"note\":\"C/4\",\"starting_point\":0.0,\"string_assignment\":1},\"1\":{\"is_rest\":false,\"length\":0.0,\"note\":\"B/3\",\"starting_point\":0.25,\"string_assignment\":1},\"2\":{\"is_rest\":false,\"length\":0.0,\"note\":\"A/3\",\"starting_point\":0.375,\"string_assignment\":2},\"3\":{\"is_rest\":false,\"length\":0.0,\"note\":\"G/3\",\"starting_point\":0.5,\"string_assignment\":2},\"ann_count\":4,\"count\":4,\"total_count\":4},\"23\":{\"0\":{\"is_rest\":false,\"length\":0.0,\"note\":\"G/3\",\"starting_point\":0.0,\"string_assignment\":2},\"1\":{\"is_rest\":false,\"length\":0.0,\"note\":\"G/3\",\"starting_point\":0.0,\"string_assignment\":3},\"2\":{\"is_rest\":false,\"length\":0.0,\"note\":\"E/3\",\"starting_point\":0.5,\"string_assignment\":3},\"ann_count\":3,\"count\":3,\"total_count\":3},\"24\":{\"0\":{\"is_rest\":false,\"length\":0.0,\"note\":\"B/3\",\"starting_point\":0.0,\"string_assignment\":1},\"ann_count\":1,\"count\":1,\"total_count\":1},\"25\":{\"0\":{\"is_rest\":false,\"length\":0.0,\"note\":\"B/3\",\"starting_point\":0.0,\"string_assignment\":1},\"1\":{\"color\":4,\"starting_point\":0.9900000095367432,\"text\":\"DS%\"},\"ann_count\":2,\"count\":1,\"total_count\":2},\"26\":{\"0\":{\"is_rest\":false,\"length\":0.0,\"note\":\"A/3\",\"starting_point\":0.0,\"string_assignment\":2},\"1\":{\"is_rest\":false,\"length\":0.0,\"note\":\"C/4\",\"starting_point\":0.5,\"string_assignment\":1},\"2\":{\"is_rest\":false,\"length\":0.0,\"note\":\"B/3\",\"starting_point\":0.75,\"string_assignment\":1},\"3\":{\"is_rest\":false,\"length\":0.0,\"note\":\"A/3\",\"starting_point\":0.875,\"string_assignment\":2},\"4\":{\"color\":6,\"starting_point\":0.0,\"text\":\"@\"},\"ann_count\":5,\"count\":4,\"total_count\":5},\"27\":{\"0\":{\"is_rest\":false,\"length\":0.0,\"note\":\"B/3\",\"starting_point\":0.0,\"string_assignment\":1},\"1\":{\"is_rest\":false,\"length\":0.0,\"note\":\"E/4\",\"starting_point\":0.25,\"string_assignment\":0},\"2\":{\"is_rest\":false,\"length\":0.0,\"note\":\"E/3\",\"starting_point\":0.5,\"string_assignment\":3},\"ann_count\":3,\"count\":3,\"total_count\":3},\"28\":{\"0\":{\"is_rest\":false,\"length\":0.0,\"note\":\"A/3\",\"starting_point\":0.0,\"string_assignment\":2},\"1\":{\"is_rest\":false,\"length\":0.0,\"note\":\"C/4\",\"starting_point\":0.5,\"string_assignment\":1},\"2\":{\"is_rest\":false,\"length\":0.0,\"note\":\"B/3\",\"starting_point\":0.75,\"string_assignment\":1},\"3\":{\"is_rest\":false,\"length\":0.0,\"note\":\"A/3\",\"starting_point\":0.875,\"string_assignment\":2},\"ann_count\":4,\"count\":4,\"total_count\":4},\"29\":{\"0\":{\"is_rest\":false,\"length\":0.0,\"note\":\"Ab/3\",\"starting_point\":0.0,\"string_assignment\":2},\"1\":{\"is_rest\":false,\"length\":0.0,\"note\":\"E/3\",\"starting_point\":0.75,\"string_assignment\":3},\"ann_count\":2,\"count\":2,\"total_count\":2},\"3\":{\"0\":{\"is_rest\":false,\"length\":0.0,\"note\":\"Ab/3\",\"starting_point\":0.0,\"string_assignment\":2},\"ann_count\":1,\"count\":1,\"total_count\":1},\"30\":{\"0\":{\"is_rest\":false,\"length\":0.0,\"note\":\"A/3\",\"starting_point\":0.0,\"string_assignment\":2},\"1\":{\"is_rest\":false,\"length\":0.0,\"note\":\"C/4\",\"starting_point\":0.5,\"string_assignment\":1},\"2\":{\"is_rest\":false,\"length\":0.0,\"note\":\"B/3\",\"starting_point\":0.75,\"string_assignment\":1},\"3\":{\"is_rest\":false,\"length\":0.0,\"note\":\"A/3\",\"starting_point\":0.875,\"string_assignment\":2},\"ann_count\":4,\"count\":4,\"total_count\":4},\"31\":{\"0\":{\"is_rest\":false,\"length\":0.0,\"note\":\"B/3\",\"starting_point\":0.0,\"string_assignment\":1},\"1\":{\"is_rest\":false,\"length\":0.0,\"note\":\"E/4\",\"starting_point\":0.25,\"string_assignment\":0},\"2\":{\"is_rest\":false,\"length\":0.0,\"note\":\"E/3\",\"starting_point\":0.5,\"string_assignment\":3},\"3\":{\"is_rest\":false,\"length\":0.0,\"note\":\"E/3\",\"starting_point\":0.75,\"string_assignment\":3},\"ann_count\":4,\"count\":4,\"total_count\":4},\"32\":{\"0\":{\"is_rest\":false,\"length\":0.0,\"note\":\"A/2\",\"starting_point\":0.0,\"string_assignment\":4},\"1\":{\"is_rest\":false,\"length\":0.0,\"note\":\"E/3\",\"starting_point\":0.0,\"string_assignment\":3},\"2\":{\"is_rest\":false,\"length\":0.0,\"note\":\"A/3\",\"starting_point\":0.0,\"string_assignment\":2},\"ann_count\":3,\"count\":3,\"total_count\":3},\"4\":{\"0\":{\"is_rest\":false,\"length\":0.0,\"note\":\"A/3\",\"starting_point\":0.0,\"string_assignment\":2},\"1\":{\"is_rest\":false,\"length\":0.0,\"note\":\"C/4\",\"starting_point\":0.5,\"string_assignment\":1},\"2\":{\"is_rest\":false,\"length\":0.0,\"note\":\"B/3\",\"starting_point\":0.75,\"string_assignment\":1},\"3\":{\"is_rest\":false,\"length\":0.0,\"note\":\"A/3\",\"starting_point\":0.875,\"string_assignment\":2},\"ann_count\":4,\"count\":4,\"total_count\":4},\"5\":{\"0\":{\"is_rest\":false,\"length\":0.0,\"note\":\"B/3\",\"starting_point\":0.0,\"string_assignment\":1},\"1\":{\"is_rest\":false,\"length\":0.0,\"note\":\"E/4\",\"starting_point\":0.25,\"string_assignment\":0},\"2\":{\"is_rest\":false,\"length\":0.0,\"note\":\"E/3\",\"starting_point\":0.5,\"string_assignment\":3},\"3\":{\"is_rest\":false,\"length\":0.0,\"note\":\"E/3\",\"starting_point\":0.75,\"string_assignment\":3},\"ann_count\":4,\"count\":4,\"total_count\":4},\"6\":{\"0\":{\"is_rest\":false,\"length\":0.0,\"note\":\"F/3\",\"starting_point\":0.0,\"string_assignment\":3},\"1\":{\"is_rest\":false,\"length\":0.0,\"note\":\"G/3\",\"starting_point\":0.125,\"string_assignment\":2},\"2\":{\"is_rest\":false,\"length\":0.0,\"note\":\"A/3\",\"starting_point\":0.25,\"string_assignment\":2},\"3\":{\"is_rest\":false,\"length\":0.0,\"note\":\"C/4\",\"starting_point\":0.5,\"string_assignment\":1},\"4\":{\"is_rest\":false,\"length\":0.0,\"note\":\"A/3\",\"starting_point\":0.75,\"string_assignment\":2},\"ann_count\":5,\"count\":5,\"total_count\":5},\"7\":{\"0\":{\"is_rest\":false,\"length\":0.0,\"note\":\"B/3\",\"starting_point\":0.0,\"string_assignment\":1},\"ann_count\":1,\"count\":1,\"total_count\":1},\"8\":{\"0\":{\"is_rest\":false,\"length\":0.0,\"note\":\"A/3\",\"starting_point\":0.0,\"string_assignment\":2},\"1\":{\"is_rest\":false,\"length\":0.0,\"note\":\"C/4\",\"starting_point\":0.5,\"string_assignment\":1},\"2\":{\"is_rest\":false,\"length\":0.0,\"note\":\"B/3\",\"starting_point\":0.75,\"string_assignment\":1},\"3\":{\"is_rest\":false,\"length\":0.0,\"note\":\"A/3\",\"starting_point\":0.875,\"string_assignment\":2},\"4\":{\"color\":4,\"starting_point\":0.0,\"text\":\"%\"},\"ann_count\":5,\"count\":4,\"total_count\":5},\"9\":{\"0\":{\"is_rest\":false,\"length\":0.0,\"note\":\"B/3\",\"starting_point\":0.0,\"string_assignment\":1},\"1\":{\"is_rest\":false,\"length\":0.0,\"note\":\"E/4\",\"starting_point\":0.25,\"string_assignment\":0},\"2\":{\"is_rest\":false,\"length\":0.0,\"note\":\"E/3\",\"starting_point\":0.5,\"string_assignment\":3},\"ann_count\":3,\"count\":3,\"total_count\":3},\"guitar\":{\"0\":{\"max_fret\":24,\"note\":\"E/4\"},\"1\":{\"max_fret\":24,\"note\":\"B/3\"},\"2\":{\"max_fret\":24,\"note\":\"G/3\"},\"3\":{\"max_fret\":24,\"note\":\"D/3\"},\"4\":{\"max_fret\":24,\"note\":\"A/2\"},\"5\":{\"max_fret\":24,\"note\":\"D/2\"},\"6\":{\"max_fret\":24,\"note\":\"B/1\"},\"nstrings\":7},\"major_key\":\"C\",\"n_measures\":33,\"time_signature_bottom\":4,\"time_signature_top\":4}"}
